gasify/__init__.py
gasify/gas.py
gasify/humidity.py
gasify/py.typed
gasify/unit.py
gasify-1.3.1.dist-info/LICENSE.txt
gasify-1.3.1.dist-info/METADATA
gasify-1.3.1.dist-info/WHEEL
gasify-1.3.1.dist-info/RECORD
