Metadata-Version: 2.1
Name: gasify
Version: 1.3.1
Summary: A module for handling data from experiments, primarily focused upon gas measurement
License: GPL-3.0-only
Author: Chris Harrison
Author-email: 629204+ravngr@users.noreply.github.com
Requires-Python: >=3.7,<4.0
Classifier: License :: OSI Approved :: GNU General Public License v3 (GPLv3)
Classifier: Programming Language :: Python :: 3
Classifier: Programming Language :: Python :: 3.7
Classifier: Programming Language :: Python :: 3.8
Classifier: Programming Language :: Python :: 3.9
Classifier: Programming Language :: Python :: 3.10
Classifier: Programming Language :: Python :: 3.11
Requires-Dist: Pint (==0.18) ; python_version < "3.8"
Requires-Dist: Pint (>=0.19.2,<0.20.0) ; python_version >= "3.8"
Requires-Dist: plenary (>=1.6.4,<2.0.0)
Requires-Dist: uncertainties (>=3.1.7,<4.0.0)
